app/__init__.py
app/app_pb2.py
app/app_pb2.pyi
app/app_pb2_grpc.py
forwarder/__init__.py
forwarder/basic_pb2.py
forwarder/basic_pb2.pyi
forwarder/basic_pb2_grpc.py
forwarder/entity_pb2.py
forwarder/entity_pb2.pyi
forwarder/entity_pb2_grpc.py
forwarder/history_pb2.py
forwarder/history_pb2.pyi
forwarder/history_pb2_grpc.py
forwarder/mq_pb2.py
forwarder/mq_pb2.pyi
forwarder/mq_pb2_grpc.py
forwarder/realtime_pb2.py
forwarder/realtime_pb2.pyi
forwarder/realtime_pb2_grpc.py
forwarder/subscribe_pb2.py
forwarder/subscribe_pb2.pyi
forwarder/subscribe_pb2_grpc.py
forwarder/trade_pb2.py
forwarder/trade_pb2.pyi
forwarder/trade_pb2_grpc.py
toc_trade_pb-0.1.0.dist-info/METADATA
toc_trade_pb-0.1.0.dist-info/WHEEL
toc_trade_pb-0.1.0.dist-info/licenses/LICENSE
toc_trade_pb-0.1.0.dist-info/RECORD
