Metadata-Version: 2.3
Name: toc-trade-pb
Version: 0.1.0
Summary: Pre-compiled Python protobuf files for ToC Trade
Project-URL: Homepage, https://github.com/ToC-Taiwan/toc-trade-protobuf
Project-URL: Issues, https://github.com/ToC-Taiwan/toc-trade-protobuf/issues
Author-email: Tim Hsu <maochindada@gmail.com>
License-File: LICENSE
Classifier: License :: OSI Approved :: MIT License
Classifier: Operating System :: OS Independent
Classifier: Programming Language :: Python :: 3
Requires-Python: >=3.11
